undetected_selenium/__init__.py
undetected_selenium/browser.py
undetected_selenium-1.1.dist-info/LICENSE
undetected_selenium-1.1.dist-info/METADATA
undetected_selenium-1.1.dist-info/WHEEL
undetected_selenium-1.1.dist-info/top_level.txt
undetected_selenium-1.1.dist-info/RECORD
