Metadata-Version: 2.1
Name: undetected-selenium
Version: 1.1
Summary: An undetected version of better selenium.
Author-email: Izaan Noman <pythonlogstest@gmail.com>
Project-URL: Homepage, https://github.com/pypa/sampleproject
Project-URL: Bug Tracker, https://github.com/pypa/sampleproject/issues
Classifier: Programming Language :: Python :: 3
Classifier: License :: OSI Approved :: MIT License
Classifier: Operating System :: OS Independent
Requires-Python: >=3.7
License-File: LICENSE
Requires-Dist: undetected-chromedriver >=3.5.4
